stampr_ai/__init__.py
stampr_ai/api.py
stampr_ai/api_client.py
stampr_ai/api_types.py
stampr_ai/cli.py
stampr_ai/config.py
stampr_ai/py.typed
stampr_ai/signature.py
stampr_ai/verifier.py
stampr_ai/providers/__init__.py
stampr_ai/providers/openai.py
stampr_ai/providers/openrouter.py
stampr_ai/utils/__init__.py
stampr_ai/utils/keys.py
stampr_ai/utils/tokenizers.py
stampr_ai-0.1.0a11.dist-info/licenses/LICENSE
stampr_ai-0.1.0a11.dist-info/METADATA
stampr_ai-0.1.0a11.dist-info/WHEEL
stampr_ai-0.1.0a11.dist-info/entry_points.txt
stampr_ai-0.1.0a11.dist-info/top_level.txt
stampr_ai-0.1.0a11.dist-info/RECORD
