Metadata-Version: 2.4
Name: stampr_ai
Version: 0.1.0a11
Summary: Live verification of AI model signatures to detect model changes
Author-email: Vasilios Mavroudis <mavroudisv@gmail.com>, Dan Ristea <dan.ristea.19@ucl.ac.uk>
License-Expression: MIT
Project-URL: Homepage, https://stampr-ai.com
Project-URL: Documentation, https://stampr-ai.com/docs
Project-URL: Repository, https://github.com/stampr-ai/stampr_ai
Project-URL: Bug Tracker, https://github.com/stampr-ai/stampr_ai/issues
Project-URL: Changelog, https://github.com/stampr-ai/stampr_ai/blob/main/CHANGELOG.md
Keywords: ai,model,verification,signature,security,llm,monitoring,testing
Classifier: Development Status :: 4 - Beta
Classifier: Intended Audience :: Developers
Classifier: Intended Audience :: Science/Research
Classifier: Operating System :: OS Independent
Classifier: Programming Language :: Python :: 3
Classifier: Programming Language :: Python :: 3.9
Classifier: Programming Language :: Python :: 3.10
Classifier: Programming Language :: Python :: 3.11
Classifier: Programming Language :: Python :: 3.12
Classifier: Topic :: Software Development :: Libraries :: Python Modules
Classifier: Topic :: Security
Classifier: Topic :: Scientific/Engineering :: Artificial Intelligence
Classifier: Topic :: System :: Monitoring
Requires-Python: >=3.9
License-File: LICENSE
Requires-Dist: requests>=2.32.4
Requires-Dist: tiktoken>=0.9.0
Requires-Dist: python-dotenv>=1.1.0
Requires-Dist: tqdm>=4.67.0
Requires-Dist: transformers[hf-xet]>=4.52.4
Requires-Dist: zstandard
Requires-Dist: brotli
Provides-Extra: openai
Requires-Dist: openai; extra == "openai"
Provides-Extra: all
Requires-Dist: stampr_ai[openai]; extra == "all"
Dynamic: license-file
